modpypes3/__init__.py
modpypes3/__main__.py
modpypes3/app.py
modpypes3/argparse.py
modpypes3/cmd.py
modpypes3/comm.py
modpypes3/console.py
modpypes3/debugging.py
modpypes3/errors.py
modpypes3/mpdu.py
modpypes3/pdu.py
modpypes3/py.typed
modpypes3/settings.py
modpypes3/ipv4/__init__.py
modpypes3/ipv4/tcp.py
tests/__init__.py
tests/clocked_test.py
tests/conftest.py
tests/state_machine.py
tests/test_1.py
tests/test__template.py
tests/trapped_classes.py
tests/utilities.py
modpypes3-0.6.dist-info/AUTHORS.rst
modpypes3-0.6.dist-info/LICENSE
modpypes3-0.6.dist-info/METADATA
modpypes3-0.6.dist-info/WHEEL
modpypes3-0.6.dist-info/top_level.txt
modpypes3-0.6.dist-info/RECORD
